byteformatter/__init__.py
byteformatter/formatter.py
smartbytesize-0.1.0.dist-info/licenses/LICENSE
smartbytesize-0.1.0.dist-info/METADATA
smartbytesize-0.1.0.dist-info/WHEEL
smartbytesize-0.1.0.dist-info/top_level.txt
smartbytesize-0.1.0.dist-info/RECORD
