Metadata-Version: 2.4
Name: smartbytesize
Version: 0.1.0
Summary: Convert bytes to a human-readable format (KB, MB, GB, etc.)
Author-email: Praveenkumar Nedumaran <creatorpravin@gmail.com>
License: MIT
Requires-Python: >=3.7
License-File: LICENSE
Dynamic: license-file
